datefns/__init__.py
datefns/datefns.py
datefns/timefns.py
datefns-0.0.1a8.dist-info/LICENSE.txt
datefns-0.0.1a8.dist-info/METADATA
datefns-0.0.1a8.dist-info/WHEEL
datefns-0.0.1a8.dist-info/top_level.txt
datefns-0.0.1a8.dist-info/RECORD
