Metadata-Version: 2.1
Name: datefns
Version: 0.0.1a8
Summary: A module providing some useful date functions
Home-page: https://github.com/ktr/datefns
Author: Kevin Ryan
Author-email: ktr@26ocb.com
License: MIT
Keywords: dates
Platform: UNKNOWN
Classifier: Development Status :: 3 - Alpha
Classifier: Intended Audience :: Developers
Classifier: Topic :: Software Development :: Build Tools
Classifier: Topic :: Office/Business
Classifier: Topic :: Software Development :: Libraries
Classifier: License :: OSI Approved :: MIT License
Classifier: Programming Language :: Python :: 3.4
Classifier: Programming Language :: Python :: 3.5
Classifier: Programming Language :: Python :: 3.6
Classifier: Programming Language :: Python :: 3.7
